sonnerrise_definitions/__init__.py
sonnerrise_definitions/cli.py
sonnerrise_definitions/models.py
sonnerrise_definitions/repository.py
sonnerrise_definitions/schemas.py
sonnerrise_definitions-0.1.0.dist-info/METADATA
sonnerrise_definitions-0.1.0.dist-info/WHEEL
sonnerrise_definitions-0.1.0.dist-info/entry_points.txt
sonnerrise_definitions-0.1.0.dist-info/RECORD
